{
    "placar": {
        "azul": 3,
        "amarelo": 0
    },
    "posse_de_bola": {
        "azul": 0,
        "amarelo": 0
    },
    "chutes": {
        "azul": 0,
        "amarelo": 0
    },
    "resets": {
        "total": 2,
        "lateral": 0,
        "endline": 2
    },
    "tempo_total": 600.1605868339539,
    "historico": [
        {
            "tempo": 10.147333145141602,
            "placar": {
                "azul": 0,
                "amarelo": 0
            },
            "posse_de_bola": {
                "azul": 0,
                "amarelo": 0
            },
            "resets": {
                "total": 0,
                "lateral": 0,
                "endline": 0
            }
        },
        {
            "tempo": 20.370447635650635,
            "placar": {
                "azul": 0,
                "amarelo": 0
            },
            "posse_de_bola": {
                "azul": 0,
                "amarelo": 0
            },
            "resets": {
                "total": 0,
                "lateral": 0,
                "endline": 0
            }
        },
        {
            "tempo": 30.822384357452393,
            "placar": {
                "azul": 0,
                "amarelo": 0
            },
            "posse_de_bola": {
                "azul": 0,
                "amarelo": 0
            },
            "resets": {
                "total": 0,
                "lateral": 0,
                "endline": 0
            }
        },
        {
            "tempo": 40.85249900817871,
            "placar": {
                "azul": 0,
                "amarelo": 0
            },
            "posse_de_bola": {
                "azul": 0,
                "amarelo": 0
            },
            "resets": {
                "total": 0,
                "lateral": 0,
                "endline": 0
            }
        },
        {
            "tempo": 50.86439847946167,
            "placar": {
                "azul": 0,
                "amarelo": 0
            },
            "posse_de_bola": {
                "azul": 0,
                "amarelo": 0
            },
            "resets": {
                "total": 0,
                "lateral": 0,
                "endline": 0
            }
        },
        {
            "tempo": 61.21952533721924,
            "placar": {
                "azul": 0,
                "amarelo": 0
            },
            "posse_de_bola": {
                "azul": 0,
                "amarelo": 0
            },
            "resets": {
                "total": 0,
                "lateral": 0,
                "endline": 0
            }
        },
        {
            "tempo": 71.25742435455322,
            "placar": {
                "azul": 0,
                "amarelo": 0
            },
            "posse_de_bola": {
                "azul": 0,
                "amarelo": 0
            },
            "resets": {
                "total": 0,
                "lateral": 0,
                "endline": 0
            }
        },
        {
            "tempo": 81.26862049102783,
            "placar": {
                "azul": 0,
                "amarelo": 0
            },
            "posse_de_bola": {
                "azul": 0,
                "amarelo": 0
            },
            "resets": {
                "total": 0,
                "lateral": 0,
                "endline": 0
            }
        },
        {
            "tempo": 91.66885614395142,
            "placar": {
                "azul": 0,
                "amarelo": 0
            },
            "posse_de_bola": {
                "azul": 0,
                "amarelo": 0
            },
            "resets": {
                "total": 0,
                "lateral": 0,
                "endline": 0
            }
        },
        {
            "tempo": 101.68236494064331,
            "placar": {
                "azul": 0,
                "amarelo": 0
            },
            "posse_de_bola": {
                "azul": 0,
                "amarelo": 0
            },
            "resets": {
                "total": 0,
                "lateral": 0,
                "endline": 0
            }
        },
        {
            "tempo": 112.10552453994751,
            "placar": {
                "azul": 0,
                "amarelo": 0
            },
            "posse_de_bola": {
                "azul": 0,
                "amarelo": 0
            },
            "resets": {
                "total": 0,
                "lateral": 0,
                "endline": 0
            }
        },
        {
            "tempo": 122.40535020828247,
            "placar": {
                "azul": 0,
                "amarelo": 0
            },
            "posse_de_bola": {
                "azul": 0,
                "amarelo": 0
            },
            "resets": {
                "total": 0,
                "lateral": 0,
                "endline": 0
            }
        },
        {
            "tempo": 132.4832320213318,
            "placar": {
                "azul": 0,
                "amarelo": 0
            },
            "posse_de_bola": {
                "azul": 0,
                "amarelo": 0
            },
            "resets": {
                "total": 0,
                "lateral": 0,
                "endline": 0
            }
        },
        {
            "tempo": 142.64203310012817,
            "placar": {
                "azul": 0,
                "amarelo": 0
            },
            "posse_de_bola": {
                "azul": 0,
                "amarelo": 0
            },
            "resets": {
                "total": 0,
                "lateral": 0,
                "endline": 0
            }
        },
        {
            "tempo": 152.92903184890747,
            "placar": {
                "azul": 0,
                "amarelo": 0
            },
            "posse_de_bola": {
                "azul": 0,
                "amarelo": 0
            },
            "resets": {
                "total": 0,
                "lateral": 0,
                "endline": 0
            }
        },
        {
            "tempo": 163.07998895645142,
            "placar": {
                "azul": 0,
                "amarelo": 0
            },
            "posse_de_bola": {
                "azul": 0,
                "amarelo": 0
            },
            "resets": {
                "total": 0,
                "lateral": 0,
                "endline": 0
            }
        },
        {
            "tempo": 173.29480648040771,
            "placar": {
                "azul": 0,
                "amarelo": 0
            },
            "posse_de_bola": {
                "azul": 0,
                "amarelo": 0
            },
            "resets": {
                "total": 0,
                "lateral": 0,
                "endline": 0
            }
        },
        {
            "tempo": 183.35684537887573,
            "placar": {
                "azul": 0,
                "amarelo": 0
            },
            "posse_de_bola": {
                "azul": 0,
                "amarelo": 0
            },
            "resets": {
                "total": 0,
                "lateral": 0,
                "endline": 0
            }
        },
        {
            "tempo": 193.78135204315186,
            "placar": {
                "azul": 0,
                "amarelo": 0
            },
            "posse_de_bola": {
                "azul": 0,
                "amarelo": 0
            },
            "resets": {
                "total": 0,
                "lateral": 0,
                "endline": 0
            }
        },
        {
            "tempo": 203.90756130218506,
            "placar": {
                "azul": 0,
                "amarelo": 0
            },
            "posse_de_bola": {
                "azul": 0,
                "amarelo": 0
            },
            "resets": {
                "total": 0,
                "lateral": 0,
                "endline": 0
            }
        },
        {
            "tempo": 213.95925283432007,
            "placar": {
                "azul": 0,
                "amarelo": 0
            },
            "posse_de_bola": {
                "azul": 0,
                "amarelo": 0
            },
            "resets": {
                "total": 0,
                "lateral": 0,
                "endline": 0
            }
        },
        {
            "tempo": 226.31701231002808,
            "placar": {
                "azul": 1,
                "amarelo": 0
            },
            "posse_de_bola": {
                "azul": 0,
                "amarelo": 0
            },
            "resets": {
                "total": 3,
                "lateral": 0,
                "endline": 3
            }
        },
        {
            "tempo": 236.48004531860352,
            "placar": {
                "azul": 1,
                "amarelo": 0
            },
            "posse_de_bola": {
                "azul": 0,
                "amarelo": 0
            },
            "resets": {
                "total": 3,
                "lateral": 0,
                "endline": 3
            }
        },
        {
            "tempo": 246.78235054016113,
            "placar": {
                "azul": 1,
                "amarelo": 0
            },
            "posse_de_bola": {
                "azul": 0,
                "amarelo": 0
            },
            "resets": {
                "total": 3,
                "lateral": 0,
                "endline": 3
            }
        },
        {
            "tempo": 257.187819480896,
            "placar": {
                "azul": 1,
                "amarelo": 0
            },
            "posse_de_bola": {
                "azul": 0,
                "amarelo": 0
            },
            "resets": {
                "total": 3,
                "lateral": 0,
                "endline": 3
            }
        },
        {
            "tempo": 267.62733459472656,
            "placar": {
                "azul": 1,
                "amarelo": 0
            },
            "posse_de_bola": {
                "azul": 0,
                "amarelo": 0
            },
            "resets": {
                "total": 3,
                "lateral": 0,
                "endline": 3
            }
        },
        {
            "tempo": 277.91446447372437,
            "placar": {
                "azul": 1,
                "amarelo": 0
            },
            "posse_de_bola": {
                "azul": 0,
                "amarelo": 0
            },
            "resets": {
                "total": 3,
                "lateral": 0,
                "endline": 3
            }
        },
        {
            "tempo": 288.29166889190674,
            "placar": {
                "azul": 1,
                "amarelo": 0
            },
            "posse_de_bola": {
                "azul": 0,
                "amarelo": 0
            },
            "resets": {
                "total": 3,
                "lateral": 0,
                "endline": 3
            }
        },
        {
            "tempo": 298.30005168914795,
            "placar": {
                "azul": 1,
                "amarelo": 0
            },
            "posse_de_bola": {
                "azul": 0,
                "amarelo": 0
            },
            "resets": {
                "total": 3,
                "lateral": 0,
                "endline": 3
            }
        },
        {
            "tempo": 308.6957335472107,
            "placar": {
                "azul": 1,
                "amarelo": 0
            },
            "posse_de_bola": {
                "azul": 0,
                "amarelo": 0
            },
            "resets": {
                "total": 3,
                "lateral": 0,
                "endline": 3
            }
        },
        {
            "tempo": 318.93097162246704,
            "placar": {
                "azul": 1,
                "amarelo": 0
            },
            "posse_de_bola": {
                "azul": 0,
                "amarelo": 0
            },
            "resets": {
                "total": 3,
                "lateral": 0,
                "endline": 3
            }
        },
        {
            "tempo": 329.23743724823,
            "placar": {
                "azul": 1,
                "amarelo": 0
            },
            "posse_de_bola": {
                "azul": 0,
                "amarelo": 0
            },
            "resets": {
                "total": 3,
                "lateral": 0,
                "endline": 3
            }
        },
        {
            "tempo": 339.59699869155884,
            "placar": {
                "azul": 1,
                "amarelo": 0
            },
            "posse_de_bola": {
                "azul": 0,
                "amarelo": 0
            },
            "resets": {
                "total": 3,
                "lateral": 0,
                "endline": 3
            }
        },
        {
            "tempo": 349.7187852859497,
            "placar": {
                "azul": 1,
                "amarelo": 0
            },
            "posse_de_bola": {
                "azul": 0,
                "amarelo": 0
            },
            "resets": {
                "total": 3,
                "lateral": 0,
                "endline": 3
            }
        },
        {
            "tempo": 360.0166440010071,
            "placar": {
                "azul": 1,
                "amarelo": 0
            },
            "posse_de_bola": {
                "azul": 0,
                "amarelo": 0
            },
            "resets": {
                "total": 3,
                "lateral": 0,
                "endline": 3
            }
        },
        {
            "tempo": 370.0591564178467,
            "placar": {
                "azul": 1,
                "amarelo": 0
            },
            "posse_de_bola": {
                "azul": 0,
                "amarelo": 0
            },
            "resets": {
                "total": 3,
                "lateral": 0,
                "endline": 3
            }
        },
        {
            "tempo": 380.3677797317505,
            "placar": {
                "azul": 1,
                "amarelo": 0
            },
            "posse_de_bola": {
                "azul": 0,
                "amarelo": 0
            },
            "resets": {
                "total": 3,
                "lateral": 0,
                "endline": 3
            }
        },
        {
            "tempo": 390.3727889060974,
            "placar": {
                "azul": 1,
                "amarelo": 0
            },
            "posse_de_bola": {
                "azul": 0,
                "amarelo": 0
            },
            "resets": {
                "total": 3,
                "lateral": 0,
                "endline": 3
            }
        },
        {
            "tempo": 400.66553354263306,
            "placar": {
                "azul": 1,
                "amarelo": 0
            },
            "posse_de_bola": {
                "azul": 0,
                "amarelo": 0
            },
            "resets": {
                "total": 3,
                "lateral": 0,
                "endline": 3
            }
        },
        {
            "tempo": 410.7988238334656,
            "placar": {
                "azul": 1,
                "amarelo": 0
            },
            "posse_de_bola": {
                "azul": 0,
                "amarelo": 0
            },
            "resets": {
                "total": 3,
                "lateral": 0,
                "endline": 3
            }
        },
        {
            "tempo": 420.85481882095337,
            "placar": {
                "azul": 1,
                "amarelo": 0
            },
            "posse_de_bola": {
                "azul": 0,
                "amarelo": 0
            },
            "resets": {
                "total": 3,
                "lateral": 0,
                "endline": 3
            }
        },
        {
            "tempo": 434.34300422668457,
            "placar": {
                "azul": 2,
                "amarelo": 0
            },
            "posse_de_bola": {
                "azul": 0,
                "amarelo": 0
            },
            "resets": {
                "total": 3,
                "lateral": 1,
                "endline": 2
            }
        },
        {
            "tempo": 444.39653158187866,
            "placar": {
                "azul": 2,
                "amarelo": 0
            },
            "posse_de_bola": {
                "azul": 0,
                "amarelo": 0
            },
            "resets": {
                "total": 3,
                "lateral": 1,
                "endline": 2
            }
        },
        {
            "tempo": 454.69489097595215,
            "placar": {
                "azul": 2,
                "amarelo": 0
            },
            "posse_de_bola": {
                "azul": 0,
                "amarelo": 0
            },
            "resets": {
                "total": 3,
                "lateral": 1,
                "endline": 2
            }
        },
        {
            "tempo": 465.02102613449097,
            "placar": {
                "azul": 2,
                "amarelo": 0
            },
            "posse_de_bola": {
                "azul": 0,
                "amarelo": 0
            },
            "resets": {
                "total": 3,
                "lateral": 1,
                "endline": 2
            }
        },
        {
            "tempo": 475.0751852989197,
            "placar": {
                "azul": 2,
                "amarelo": 0
            },
            "posse_de_bola": {
                "azul": 0,
                "amarelo": 0
            },
            "resets": {
                "total": 3,
                "lateral": 1,
                "endline": 2
            }
        },
        {
            "tempo": 485.4553818702698,
            "placar": {
                "azul": 2,
                "amarelo": 0
            },
            "posse_de_bola": {
                "azul": 0,
                "amarelo": 0
            },
            "resets": {
                "total": 3,
                "lateral": 1,
                "endline": 2
            }
        },
        {
            "tempo": 495.84648609161377,
            "placar": {
                "azul": 2,
                "amarelo": 0
            },
            "posse_de_bola": {
                "azul": 0,
                "amarelo": 0
            },
            "resets": {
                "total": 3,
                "lateral": 1,
                "endline": 2
            }
        },
        {
            "tempo": 505.84815740585327,
            "placar": {
                "azul": 2,
                "amarelo": 0
            },
            "posse_de_bola": {
                "azul": 0,
                "amarelo": 0
            },
            "resets": {
                "total": 3,
                "lateral": 1,
                "endline": 2
            }
        },
        {
            "tempo": 516.2649869918823,
            "placar": {
                "azul": 2,
                "amarelo": 0
            },
            "posse_de_bola": {
                "azul": 0,
                "amarelo": 0
            },
            "resets": {
                "total": 3,
                "lateral": 1,
                "endline": 2
            }
        },
        {
            "tempo": 526.2654423713684,
            "placar": {
                "azul": 2,
                "amarelo": 0
            },
            "posse_de_bola": {
                "azul": 0,
                "amarelo": 0
            },
            "resets": {
                "total": 3,
                "lateral": 1,
                "endline": 2
            }
        },
        {
            "tempo": 536.6408348083496,
            "placar": {
                "azul": 2,
                "amarelo": 0
            },
            "posse_de_bola": {
                "azul": 0,
                "amarelo": 0
            },
            "resets": {
                "total": 3,
                "lateral": 1,
                "endline": 2
            }
        },
        {
            "tempo": 546.9984292984009,
            "placar": {
                "azul": 2,
                "amarelo": 0
            },
            "posse_de_bola": {
                "azul": 0,
                "amarelo": 0
            },
            "resets": {
                "total": 3,
                "lateral": 1,
                "endline": 2
            }
        },
        {
            "tempo": 557.0395112037659,
            "placar": {
                "azul": 2,
                "amarelo": 0
            },
            "posse_de_bola": {
                "azul": 0,
                "amarelo": 0
            },
            "resets": {
                "total": 3,
                "lateral": 1,
                "endline": 2
            }
        },
        {
            "tempo": 567.4641489982605,
            "placar": {
                "azul": 2,
                "amarelo": 0
            },
            "posse_de_bola": {
                "azul": 0,
                "amarelo": 0
            },
            "resets": {
                "total": 3,
                "lateral": 1,
                "endline": 2
            }
        },
        {
            "tempo": 577.5436758995056,
            "placar": {
                "azul": 2,
                "amarelo": 0
            },
            "posse_de_bola": {
                "azul": 0,
                "amarelo": 0
            },
            "resets": {
                "total": 3,
                "lateral": 1,
                "endline": 2
            }
        },
        {
            "tempo": 587.7789616584778,
            "placar": {
                "azul": 3,
                "amarelo": 0
            },
            "posse_de_bola": {
                "azul": 0,
                "amarelo": 0
            },
            "resets": {
                "total": 2,
                "lateral": 0,
                "endline": 2
            }
        },
        {
            "tempo": 597.8369116783142,
            "placar": {
                "azul": 3,
                "amarelo": 0
            },
            "posse_de_bola": {
                "azul": 0,
                "amarelo": 0
            },
            "resets": {
                "total": 2,
                "lateral": 0,
                "endline": 2
            }
        }
    ],
    "vencedor": "Azul",
    "config": {
        "duracao": 600,
        "speed_up": 50,
        "num_robos": {
            "azul": 3,
            "amarelo": 3
        }
    }
}