{
    "placar": {
        "azul": 7,
        "amarelo": 0
    },
    "posse_de_bola": {
        "azul": 0,
        "amarelo": 0
    },
    "chutes": {
        "azul": 0,
        "amarelo": 0
    },
    "resets": {
        "total": 2,
        "lateral": 0,
        "endline": 2
    },
    "tempo_total": 600.1986026763916,
    "historico": [
        {
            "tempo": 10.35081148147583,
            "placar": {
                "azul": 0,
                "amarelo": 0
            },
            "posse_de_bola": {
                "azul": 0,
                "amarelo": 0
            },
            "resets": {
                "total": 0,
                "lateral": 0,
                "endline": 0
            }
        },
        {
            "tempo": 20.36118507385254,
            "placar": {
                "azul": 0,
                "amarelo": 0
            },
            "posse_de_bola": {
                "azul": 0,
                "amarelo": 0
            },
            "resets": {
                "total": 0,
                "lateral": 0,
                "endline": 0
            }
        },
        {
            "tempo": 30.52419424057007,
            "placar": {
                "azul": 0,
                "amarelo": 0
            },
            "posse_de_bola": {
                "azul": 0,
                "amarelo": 0
            },
            "resets": {
                "total": 0,
                "lateral": 0,
                "endline": 0
            }
        },
        {
            "tempo": 40.79403877258301,
            "placar": {
                "azul": 0,
                "amarelo": 0
            },
            "posse_de_bola": {
                "azul": 0,
                "amarelo": 0
            },
            "resets": {
                "total": 0,
                "lateral": 0,
                "endline": 0
            }
        },
        {
            "tempo": 50.95105171203613,
            "placar": {
                "azul": 1,
                "amarelo": 0
            },
            "posse_de_bola": {
                "azul": 0,
                "amarelo": 0
            },
            "resets": {
                "total": 0,
                "lateral": 0,
                "endline": 0
            }
        },
        {
            "tempo": 61.193645000457764,
            "placar": {
                "azul": 1,
                "amarelo": 0
            },
            "posse_de_bola": {
                "azul": 0,
                "amarelo": 0
            },
            "resets": {
                "total": 0,
                "lateral": 0,
                "endline": 0
            }
        },
        {
            "tempo": 71.58427238464355,
            "placar": {
                "azul": 1,
                "amarelo": 0
            },
            "posse_de_bola": {
                "azul": 0,
                "amarelo": 0
            },
            "resets": {
                "total": 0,
                "lateral": 0,
                "endline": 0
            }
        },
        {
            "tempo": 81.95953369140625,
            "placar": {
                "azul": 1,
                "amarelo": 0
            },
            "posse_de_bola": {
                "azul": 0,
                "amarelo": 0
            },
            "resets": {
                "total": 0,
                "lateral": 0,
                "endline": 0
            }
        },
        {
            "tempo": 92.42370128631592,
            "placar": {
                "azul": 1,
                "amarelo": 0
            },
            "posse_de_bola": {
                "azul": 0,
                "amarelo": 0
            },
            "resets": {
                "total": 0,
                "lateral": 0,
                "endline": 0
            }
        },
        {
            "tempo": 102.82949209213257,
            "placar": {
                "azul": 1,
                "amarelo": 0
            },
            "posse_de_bola": {
                "azul": 0,
                "amarelo": 0
            },
            "resets": {
                "total": 0,
                "lateral": 0,
                "endline": 0
            }
        },
        {
            "tempo": 113.25396299362183,
            "placar": {
                "azul": 1,
                "amarelo": 0
            },
            "posse_de_bola": {
                "azul": 0,
                "amarelo": 0
            },
            "resets": {
                "total": 0,
                "lateral": 0,
                "endline": 0
            }
        },
        {
            "tempo": 123.2567548751831,
            "placar": {
                "azul": 1,
                "amarelo": 0
            },
            "posse_de_bola": {
                "azul": 0,
                "amarelo": 0
            },
            "resets": {
                "total": 0,
                "lateral": 0,
                "endline": 0
            }
        },
        {
            "tempo": 133.49206447601318,
            "placar": {
                "azul": 2,
                "amarelo": 0
            },
            "posse_de_bola": {
                "azul": 0,
                "amarelo": 0
            },
            "resets": {
                "total": 0,
                "lateral": 0,
                "endline": 0
            }
        },
        {
            "tempo": 143.6550736427307,
            "placar": {
                "azul": 2,
                "amarelo": 0
            },
            "posse_de_bola": {
                "azul": 0,
                "amarelo": 0
            },
            "resets": {
                "total": 0,
                "lateral": 0,
                "endline": 0
            }
        },
        {
            "tempo": 153.72475385665894,
            "placar": {
                "azul": 2,
                "amarelo": 0
            },
            "posse_de_bola": {
                "azul": 0,
                "amarelo": 0
            },
            "resets": {
                "total": 0,
                "lateral": 0,
                "endline": 0
            }
        },
        {
            "tempo": 168.5992956161499,
            "placar": {
                "azul": 3,
                "amarelo": 0
            },
            "posse_de_bola": {
                "azul": 0,
                "amarelo": 0
            },
            "resets": {
                "total": 0,
                "lateral": 0,
                "endline": 0
            }
        },
        {
            "tempo": 178.95090579986572,
            "placar": {
                "azul": 3,
                "amarelo": 0
            },
            "posse_de_bola": {
                "azul": 0,
                "amarelo": 0
            },
            "resets": {
                "total": 0,
                "lateral": 0,
                "endline": 0
            }
        },
        {
            "tempo": 189.12335634231567,
            "placar": {
                "azul": 3,
                "amarelo": 0
            },
            "posse_de_bola": {
                "azul": 0,
                "amarelo": 0
            },
            "resets": {
                "total": 0,
                "lateral": 0,
                "endline": 0
            }
        },
        {
            "tempo": 202.4774670600891,
            "placar": {
                "azul": 4,
                "amarelo": 0
            },
            "posse_de_bola": {
                "azul": 0,
                "amarelo": 0
            },
            "resets": {
                "total": 0,
                "lateral": 0,
                "endline": 0
            }
        },
        {
            "tempo": 212.60571479797363,
            "placar": {
                "azul": 4,
                "amarelo": 0
            },
            "posse_de_bola": {
                "azul": 0,
                "amarelo": 0
            },
            "resets": {
                "total": 0,
                "lateral": 0,
                "endline": 0
            }
        },
        {
            "tempo": 222.83480167388916,
            "placar": {
                "azul": 4,
                "amarelo": 0
            },
            "posse_de_bola": {
                "azul": 0,
                "amarelo": 0
            },
            "resets": {
                "total": 0,
                "lateral": 0,
                "endline": 0
            }
        },
        {
            "tempo": 232.84974098205566,
            "placar": {
                "azul": 4,
                "amarelo": 0
            },
            "posse_de_bola": {
                "azul": 0,
                "amarelo": 0
            },
            "resets": {
                "total": 0,
                "lateral": 0,
                "endline": 0
            }
        },
        {
            "tempo": 243.70951652526855,
            "placar": {
                "azul": 5,
                "amarelo": 0
            },
            "posse_de_bola": {
                "azul": 0,
                "amarelo": 0
            },
            "resets": {
                "total": 0,
                "lateral": 0,
                "endline": 0
            }
        },
        {
            "tempo": 254.08945083618164,
            "placar": {
                "azul": 5,
                "amarelo": 0
            },
            "posse_de_bola": {
                "azul": 0,
                "amarelo": 0
            },
            "resets": {
                "total": 0,
                "lateral": 0,
                "endline": 0
            }
        },
        {
            "tempo": 264.12572860717773,
            "placar": {
                "azul": 5,
                "amarelo": 0
            },
            "posse_de_bola": {
                "azul": 0,
                "amarelo": 0
            },
            "resets": {
                "total": 0,
                "lateral": 0,
                "endline": 0
            }
        },
        {
            "tempo": 274.5060443878174,
            "placar": {
                "azul": 5,
                "amarelo": 0
            },
            "posse_de_bola": {
                "azul": 0,
                "amarelo": 0
            },
            "resets": {
                "total": 0,
                "lateral": 0,
                "endline": 0
            }
        },
        {
            "tempo": 284.5265030860901,
            "placar": {
                "azul": 5,
                "amarelo": 0
            },
            "posse_de_bola": {
                "azul": 0,
                "amarelo": 0
            },
            "resets": {
                "total": 0,
                "lateral": 0,
                "endline": 0
            }
        },
        {
            "tempo": 294.52853202819824,
            "placar": {
                "azul": 5,
                "amarelo": 0
            },
            "posse_de_bola": {
                "azul": 0,
                "amarelo": 0
            },
            "resets": {
                "total": 0,
                "lateral": 0,
                "endline": 0
            }
        },
        {
            "tempo": 304.96147871017456,
            "placar": {
                "azul": 5,
                "amarelo": 0
            },
            "posse_de_bola": {
                "azul": 0,
                "amarelo": 0
            },
            "resets": {
                "total": 0,
                "lateral": 0,
                "endline": 0
            }
        },
        {
            "tempo": 315.4230833053589,
            "placar": {
                "azul": 5,
                "amarelo": 0
            },
            "posse_de_bola": {
                "azul": 0,
                "amarelo": 0
            },
            "resets": {
                "total": 0,
                "lateral": 0,
                "endline": 0
            }
        },
        {
            "tempo": 325.7121682167053,
            "placar": {
                "azul": 5,
                "amarelo": 0
            },
            "posse_de_bola": {
                "azul": 0,
                "amarelo": 0
            },
            "resets": {
                "total": 0,
                "lateral": 0,
                "endline": 0
            }
        },
        {
            "tempo": 335.7444763183594,
            "placar": {
                "azul": 5,
                "amarelo": 0
            },
            "posse_de_bola": {
                "azul": 0,
                "amarelo": 0
            },
            "resets": {
                "total": 0,
                "lateral": 0,
                "endline": 0
            }
        },
        {
            "tempo": 345.7504391670227,
            "placar": {
                "azul": 5,
                "amarelo": 0
            },
            "posse_de_bola": {
                "azul": 0,
                "amarelo": 0
            },
            "resets": {
                "total": 0,
                "lateral": 0,
                "endline": 0
            }
        },
        {
            "tempo": 355.77845573425293,
            "placar": {
                "azul": 5,
                "amarelo": 0
            },
            "posse_de_bola": {
                "azul": 0,
                "amarelo": 0
            },
            "resets": {
                "total": 0,
                "lateral": 0,
                "endline": 0
            }
        },
        {
            "tempo": 366.1826968193054,
            "placar": {
                "azul": 5,
                "amarelo": 0
            },
            "posse_de_bola": {
                "azul": 0,
                "amarelo": 0
            },
            "resets": {
                "total": 0,
                "lateral": 0,
                "endline": 0
            }
        },
        {
            "tempo": 376.57577991485596,
            "placar": {
                "azul": 5,
                "amarelo": 0
            },
            "posse_de_bola": {
                "azul": 0,
                "amarelo": 0
            },
            "resets": {
                "total": 0,
                "lateral": 0,
                "endline": 0
            }
        },
        {
            "tempo": 386.6443395614624,
            "placar": {
                "azul": 5,
                "amarelo": 0
            },
            "posse_de_bola": {
                "azul": 0,
                "amarelo": 0
            },
            "resets": {
                "total": 0,
                "lateral": 0,
                "endline": 0
            }
        },
        {
            "tempo": 396.9300866127014,
            "placar": {
                "azul": 5,
                "amarelo": 0
            },
            "posse_de_bola": {
                "azul": 0,
                "amarelo": 0
            },
            "resets": {
                "total": 0,
                "lateral": 0,
                "endline": 0
            }
        },
        {
            "tempo": 407.03303813934326,
            "placar": {
                "azul": 5,
                "amarelo": 0
            },
            "posse_de_bola": {
                "azul": 0,
                "amarelo": 0
            },
            "resets": {
                "total": 0,
                "lateral": 0,
                "endline": 0
            }
        },
        {
            "tempo": 417.37390756607056,
            "placar": {
                "azul": 5,
                "amarelo": 0
            },
            "posse_de_bola": {
                "azul": 0,
                "amarelo": 0
            },
            "resets": {
                "total": 0,
                "lateral": 0,
                "endline": 0
            }
        },
        {
            "tempo": 427.39923000335693,
            "placar": {
                "azul": 6,
                "amarelo": 0
            },
            "posse_de_bola": {
                "azul": 0,
                "amarelo": 0
            },
            "resets": {
                "total": 2,
                "lateral": 0,
                "endline": 2
            }
        },
        {
            "tempo": 437.7691626548767,
            "placar": {
                "azul": 6,
                "amarelo": 0
            },
            "posse_de_bola": {
                "azul": 0,
                "amarelo": 0
            },
            "resets": {
                "total": 2,
                "lateral": 0,
                "endline": 2
            }
        },
        {
            "tempo": 447.8324294090271,
            "placar": {
                "azul": 6,
                "amarelo": 0
            },
            "posse_de_bola": {
                "azul": 0,
                "amarelo": 0
            },
            "resets": {
                "total": 2,
                "lateral": 0,
                "endline": 2
            }
        },
        {
            "tempo": 458.22237730026245,
            "placar": {
                "azul": 6,
                "amarelo": 0
            },
            "posse_de_bola": {
                "azul": 0,
                "amarelo": 0
            },
            "resets": {
                "total": 2,
                "lateral": 0,
                "endline": 2
            }
        },
        {
            "tempo": 468.2597279548645,
            "placar": {
                "azul": 6,
                "amarelo": 0
            },
            "posse_de_bola": {
                "azul": 0,
                "amarelo": 0
            },
            "resets": {
                "total": 2,
                "lateral": 0,
                "endline": 2
            }
        },
        {
            "tempo": 478.6163091659546,
            "placar": {
                "azul": 6,
                "amarelo": 0
            },
            "posse_de_bola": {
                "azul": 0,
                "amarelo": 0
            },
            "resets": {
                "total": 2,
                "lateral": 0,
                "endline": 2
            }
        },
        {
            "tempo": 488.666296005249,
            "placar": {
                "azul": 6,
                "amarelo": 0
            },
            "posse_de_bola": {
                "azul": 0,
                "amarelo": 0
            },
            "resets": {
                "total": 2,
                "lateral": 0,
                "endline": 2
            }
        },
        {
            "tempo": 499.03942346572876,
            "placar": {
                "azul": 6,
                "amarelo": 0
            },
            "posse_de_bola": {
                "azul": 0,
                "amarelo": 0
            },
            "resets": {
                "total": 2,
                "lateral": 0,
                "endline": 2
            }
        },
        {
            "tempo": 509.1008186340332,
            "placar": {
                "azul": 6,
                "amarelo": 0
            },
            "posse_de_bola": {
                "azul": 0,
                "amarelo": 0
            },
            "resets": {
                "total": 2,
                "lateral": 0,
                "endline": 2
            }
        },
        {
            "tempo": 519.101893901825,
            "placar": {
                "azul": 6,
                "amarelo": 0
            },
            "posse_de_bola": {
                "azul": 0,
                "amarelo": 0
            },
            "resets": {
                "total": 2,
                "lateral": 0,
                "endline": 2
            }
        },
        {
            "tempo": 529.499614238739,
            "placar": {
                "azul": 6,
                "amarelo": 0
            },
            "posse_de_bola": {
                "azul": 0,
                "amarelo": 0
            },
            "resets": {
                "total": 2,
                "lateral": 0,
                "endline": 2
            }
        },
        {
            "tempo": 539.5254492759705,
            "placar": {
                "azul": 6,
                "amarelo": 0
            },
            "posse_de_bola": {
                "azul": 0,
                "amarelo": 0
            },
            "resets": {
                "total": 2,
                "lateral": 0,
                "endline": 2
            }
        },
        {
            "tempo": 549.8721957206726,
            "placar": {
                "azul": 6,
                "amarelo": 0
            },
            "posse_de_bola": {
                "azul": 0,
                "amarelo": 0
            },
            "resets": {
                "total": 2,
                "lateral": 0,
                "endline": 2
            }
        },
        {
            "tempo": 559.9172949790955,
            "placar": {
                "azul": 6,
                "amarelo": 0
            },
            "posse_de_bola": {
                "azul": 0,
                "amarelo": 0
            },
            "resets": {
                "total": 2,
                "lateral": 0,
                "endline": 2
            }
        },
        {
            "tempo": 570.3021049499512,
            "placar": {
                "azul": 6,
                "amarelo": 0
            },
            "posse_de_bola": {
                "azul": 0,
                "amarelo": 0
            },
            "resets": {
                "total": 2,
                "lateral": 0,
                "endline": 2
            }
        },
        {
            "tempo": 584.1305494308472,
            "placar": {
                "azul": 7,
                "amarelo": 0
            },
            "posse_de_bola": {
                "azul": 0,
                "amarelo": 0
            },
            "resets": {
                "total": 2,
                "lateral": 0,
                "endline": 2
            }
        },
        {
            "tempo": 594.4401383399963,
            "placar": {
                "azul": 7,
                "amarelo": 0
            },
            "posse_de_bola": {
                "azul": 0,
                "amarelo": 0
            },
            "resets": {
                "total": 2,
                "lateral": 0,
                "endline": 2
            }
        }
    ],
    "vencedor": "Azul",
    "config": {
        "duracao": 600,
        "speed_up": 50,
        "num_robos": {
            "azul": 3,
            "amarelo": 3
        }
    }
}